pyproject.toml
seisfwi/__init__.py
seisfwi/plot/Plot.py
seisfwi/plot/__init__.py
seisfwi/problem/__init__.py
seisfwi/problem/problem.py
seisfwi/propagator/__init__.py
seisfwi/propagator/analytical.py
seisfwi/propagator/elastic.py
seisfwi/propagator/model.py
seisfwi/propagator/src/Boundary.cu
seisfwi/propagator/src/Boundary.h
seisfwi/propagator/src/Cpml.cu
seisfwi/propagator/src/Cpml.h
seisfwi/propagator/src/IsoAcousticKernel.cu
seisfwi/propagator/src/IsoElasticKernel.cu
seisfwi/propagator/src/IsoOperator.cu
seisfwi/propagator/src/IsoOperator.h
seisfwi/propagator/src/Model.cu
seisfwi/propagator/src/Model.h
seisfwi/propagator/src/Parameter.cpp
seisfwi/propagator/src/Parameter.h
seisfwi/propagator/src/Survey.cu
seisfwi/propagator/src/Survey.h
seisfwi/propagator/src/build/.ninja_deps
seisfwi/propagator/src/build/.ninja_log
seisfwi/propagator/src/build/build.ninja
seisfwi/propagator/src/libAPP.cpp
seisfwi/propagator/src/rapidjson/allocators.h
seisfwi/propagator/src/rapidjson/cursorstreamwrapper.h
seisfwi/propagator/src/rapidjson/document.h
seisfwi/propagator/src/rapidjson/encodedstream.h
seisfwi/propagator/src/rapidjson/encodings.h
seisfwi/propagator/src/rapidjson/error/en.h
seisfwi/propagator/src/rapidjson/error/error.h
seisfwi/propagator/src/rapidjson/filereadstream.h
seisfwi/propagator/src/rapidjson/filewritestream.h
seisfwi/propagator/src/rapidjson/fwd.h
seisfwi/propagator/src/rapidjson/internal/biginteger.h
seisfwi/propagator/src/rapidjson/internal/diyfp.h
seisfwi/propagator/src/rapidjson/internal/dtoa.h
seisfwi/propagator/src/rapidjson/internal/ieee754.h
seisfwi/propagator/src/rapidjson/internal/itoa.h
seisfwi/propagator/src/rapidjson/internal/meta.h
seisfwi/propagator/src/rapidjson/internal/pow10.h
seisfwi/propagator/src/rapidjson/internal/regex.h
seisfwi/propagator/src/rapidjson/internal/stack.h
seisfwi/propagator/src/rapidjson/internal/strfunc.h
seisfwi/propagator/src/rapidjson/internal/strtod.h
seisfwi/propagator/src/rapidjson/internal/swap.h
seisfwi-0.0.1.dist-info/LICENSE
seisfwi-0.0.1.dist-info/METADATA
seisfwi-0.0.1.dist-info/WHEEL
seisfwi-0.0.1.dist-info/RECORD
