Metadata-Version: 2.1
Name: seisfwi
Version: 0.0.1
Summary: Full-waveform Inversion solution for high-resolution subsurface imaging in Exploration and Environmental Seismology
License: Apache-2.0
Author: Haipeng Li
Author-email: haipeng@stanford.edu
Requires-Python: >=3.9,<3.12
Classifier: Development Status :: 2 - Pre-Alpha
Classifier: Environment :: Console
Classifier: Intended Audience :: Developers
Classifier: Intended Audience :: Science/Research
Classifier: License :: OSI Approved :: Apache Software License
Classifier: Operating System :: OS Independent
Classifier: Programming Language :: Python
Classifier: Programming Language :: Python :: 3
Classifier: Programming Language :: Python :: 3.9
Classifier: Programming Language :: Python :: 3.10
Classifier: Programming Language :: Python :: 3.11
Classifier: Topic :: Scientific/Engineering
Classifier: Topic :: Scientific/Engineering :: Physics
Requires-Dist: matplotlib (>=3.7.1,<4.0.0)
Requires-Dist: numpy (>=1.25.0,<2.0.0)
Requires-Dist: scipy (>=1.10.1,<2.0.0)
Requires-Dist: torch (>=2.0.1,<3.0.0)
